signature_snvs/__init__.py
signature_snvs/signature_snvs.py
signature_snvs/signature_snvs_cli.py
signature_snvs/helpers/__init__.py
signature_snvs/helpers/helpers.py
Signature_SNVs-0.0.1.dist-info/LICENSE.txt
Signature_SNVs-0.0.1.dist-info/METADATA
Signature_SNVs-0.0.1.dist-info/WHEEL
Signature_SNVs-0.0.1.dist-info/top_level.txt
Signature_SNVs-0.0.1.dist-info/RECORD
