Metadata-Version: 2.1
Name: Signature-SNVs
Version: 0.0.1
Summary: A package to produce signature SNVs for source tracking with methods like FEAST. Given a set of samples representing the sink and source of interest, and a species for which you have snps MIDAS output, you can run this method.
Author-email: "Leah Briscoe, Eran Halperin, Nandita Garud" <leahpbriscoe@gmail.com>
Project-URL: Homepage, https://github.com/garudlab/Signature-SNVs
Project-URL: Bug Tracker, https://github.com/garudlab/Signature-SNVs/issues
Classifier: Programming Language :: Python :: 3
Classifier: License :: OSI Approved :: MIT License
Classifier: Operating System :: OS Independent
Requires-Python: >=3.0
License-File: LICENSE.txt
Requires-Dist: numpy (>=1.20.3)
Requires-Dist: scipy (>=1.7.1)
Requires-Dist: pyyaml (>=6.0)
Requires-Dist: pandas (>=1.3.4)
Requires-Dist: bz2file (>=0.98)
